README
setup.cfg
setup.py
setuptools_dummy.py
debian/README.Debian
debian/changelog
debian/compat
debian/control
debian/copyright
debian/pycompat
debian/pyversions
debian/rules
dist/setuptools_dummy-0.1.0.0.tar.gz
setuptools_dummy.egg-info/PKG-INFO
setuptools_dummy.egg-info/SOURCES.txt
setuptools_dummy.egg-info/dependency_links.txt
setuptools_dummy.egg-info/entry_points.txt
setuptools_dummy.egg-info/top_level.txt